{
  "main": {
    "id": "ad990e90a5b41272",
    "type": "split",
    "children": [
      {
        "id": "ddb19f45991f32de",
        "type": "tabs",
        "children": [
          {
            "id": "4c8c53a0397017b7",
            "type": "leaf",
            "state": {
              "type": "markdown",
              "state": {
                "file": "content/posts/post-lite-four/index.md",
                "mode": "source",
                "source": false
              }
            }
          }
        ]
      }
    ],
    "direction": "vertical"
  },
  "left": {
    "id": "73de1a7bff63ab61",
    "type": "mobile-drawer",
    "children": [
      {
        "id": "ab2ba344825278c5",
        "type": "leaf",
        "state": {
          "type": "file-explorer",
          "state": {
            "sortOrder": "alphabetical"
          }
        }
      },
      {
        "id": "88b3f6f8498960df",
        "type": "leaf",
        "state": {
          "type": "search",
          "state": {
            "query": "",
            "matchingCase": false,
            "explainSearch": false,
            "collapseAll": false,
            "extraContext": false,
            "sortOrder": "alphabetical"
          }
        }
      },
      {
        "id": "00f65d56e84ca7c8",
        "type": "leaf",
        "state": {
          "type": "tag",
          "state": {
            "sortOrder": "frequency",
            "useHierarchy": true
          }
        }
      },
      {
        "id": "f7617a5782c98aed",
        "type": "leaf",
        "state": {
          "type": "starred",
          "state": {}
        }
      }
    ],
    "currentTab": 0
  },
  "right": {
    "id": "ec1e1e9cae564e6b",
    "type": "mobile-drawer",
    "children": [
      {
        "id": "87ad91f56bd84f10",
        "type": "leaf",
        "state": {
          "type": "backlink",
          "state": {
            "file": "content/posts/post-lite-four/index.md",
            "collapseAll": false,
            "extraContext": false,
            "sortOrder": "alphabetical",
            "showSearch": false,
            "searchQuery": "",
            "backlinkCollapsed": false,
            "unlinkedCollapsed": true
          }
        }
      },
      {
        "id": "d83866ecfcc6b21b",
        "type": "leaf",
        "state": {
          "type": "outgoing-link",
          "state": {
            "file": "content/posts/post-lite-four/index.md",
            "linksCollapsed": false,
            "unlinkedCollapsed": true
          }
        }
      },
      {
        "id": "0774d28145863332",
        "type": "leaf",
        "state": {
          "type": "outline",
          "state": {
            "file": "content/posts/post-lite-four/index.md"
          }
        }
      }
    ],
    "currentTab": 0
  },
  "active": "4c8c53a0397017b7",
  "lastOpenFiles": []
}